inmobisimple
