Metadata-Version: 1.0
Name: inmobisimple
Version: 0.1.1
Summary: An unofficial python wrapper for Inmobi Publisher Reporting API.
Home-page: UNKNOWN
Author: Rajat Singh Panwar
Author-email: onlyraj720@gmail.com
License: GNU GPL v3
Platform: UNKNOWN
